stainwarpy/__init__.py
stainwarpy/metrics.py
stainwarpy/preprocess.py
stainwarpy/reg.py
stainwarpy/regPipeline.py
stainwarpy/reg_cli.py
stainwarpy-0.2.3.dist-info/licenses/LICENSE
stainwarpy-0.2.3.dist-info/licenses/LICENSE_HISTOMICSTK.txt
stainwarpy-0.2.3.dist-info/METADATA
stainwarpy-0.2.3.dist-info/WHEEL
stainwarpy-0.2.3.dist-info/entry_points.txt
stainwarpy-0.2.3.dist-info/top_level.txt
stainwarpy-0.2.3.dist-info/RECORD
