Metadata-Version: 2.4
Name: stainwarpy
Version: 0.2.3
Summary: Tools for image registration between multiplexed and HnE stained tissue images
Home-page: https://github.com/tckumarasekara/stainwarpy
Author: Thusheera Kumarasekara
Author-email: tckumarasekara@gmail.com
License: MIT
Classifier: Programming Language :: Python :: 3
Classifier: License :: OSI Approved :: MIT License
Classifier: Operating System :: OS Independent
Requires-Python: >=3.11
License-File: LICENSE
License-File: LICENSE_HISTOMICSTK.txt
Requires-Dist: numpy>=2.2
Requires-Dist: tifffile>=2025.5
Requires-Dist: imagecodecs>=2025.11
Requires-Dist: scikit-image>=0.25
Requires-Dist: scipy>=1.16
Requires-Dist: typer[all]>=0.20
Provides-Extra: plots
Requires-Dist: matplotlib; extra == "plots"
Dynamic: author
Dynamic: author-email
Dynamic: classifier
Dynamic: description
Dynamic: description-content-type
Dynamic: home-page
Dynamic: license
Dynamic: license-file
Dynamic: provides-extra
Dynamic: requires-dist
Dynamic: requires-python
Dynamic: summary
